pymcuboot/__init__.py
pymcuboot/version.py
pymcuboot-0.0.0.3.dist-info/LICENSE.txt
pymcuboot-0.0.0.3.dist-info/METADATA
pymcuboot-0.0.0.3.dist-info/WHEEL
pymcuboot-0.0.0.3.dist-info/top_level.txt
pymcuboot-0.0.0.3.dist-info/RECORD
